{"bun":{"array":{"output":"1","Time":35},"loop":{"output":"0","Time":25}},"node":{"array":{"output":"0","Time":238},"loop":{"output":"1","Time":43}},"deno":{"array":{"output":"3","Time":348},"loop":{"output":"0","Time":31}},"graaljs":{"array":{"output":"3","Time":81},"loop":{"output":"2","Time":27}},"hermes":{"array":{"output":"1","Time":38},"loop":{"output":"1","Time":20}},"llrt":{"array":{"output":"1","Time":52},"loop":{"output":"2","Time":17}},"tjs":{"array":{"output":"0","Time":46},"loop":{"output":"1","Time":24}},"qjs":{"array":{"output":"0","Time":15},"loop":{"output":"2","Time":14}},"qjs-ng":{"array":{"output":"1","Time":18},"loop":{"output":"1","Time":17}},"mujs":{"array":{"output":"2","Time":24},"loop":{"output":"20","Time":37}},"xst":{"array":{"output":"176","Time":207},"loop":{"output":"17","Time":37}},"jsc":{"array":{"output":"4","Time":218},"loop":{"output":"1","Time":25}},"d8":{"array":{"output":"6","Time":139},"loop":{"output":"6","Time":29}},"js":{"array":{"output":"5","Time":355},"loop":{"output":"1","Time":32}},"jerry":{"array":{"output":"3","Time":25},"loop":{"output":"3","Time":19}},"primjs":{"array":{"output":"2","Time":25},"loop":{"output":"0","Time":16}},"rquickjs":{"array":{"output":"1","Time":23},"loop":{"output":"2","Time":14}},"duk":{"array":{"output":"2","Time":25},"loop":{"output":"11","Time":28}},"nova":{"array":{"output":"11","Time":49},"loop":{"output":"21","Time":35}},"engine262":{"array":{"output":"758","Time":919},"loop":{"output":"549","Time":663}},"ladybird":{"array":{"output":"\u001b[35;1m1\u001b[0m","Time":50},"loop":{"output":"\u001b[35;1m1\u001b[0m","Time":24}},"goja":{"array":{"output":"","Time":84},"loop":{"output":"","Time":35}},"kiesel":{"array":{"output":"9","Time":51},"loop":{"output":"61","Time":81}},"mozjs":{"array":{"output":"4","Time":78},"loop":{"output":"1","Time":26}},"jint-cli":{"array":{"output":"45","Time":282},"loop":{"output":"23","Time":140}},"dune":{"array":{"output":"5","Time":135},"loop":{"output":"0","Time":26}},"jjs":{"array":{"output":"68","Time":901},"loop":{"output":"42","Time":682}},"rhino":{"array":{"output":"","Time":24},"loop":{"output":"","Time":17}},"njs":{"array":{"output":"1","Time":30},"loop":{"output":"7","Time":28}},"ringo":{"array":{"output":"9","Time":528},"loop":{"output":"8","Time":318}},"spiderfire":{"array":{"output":"3","Time":151},"loop":{"output":"1","Time":30}},"hako":{"array":{"output":"","Time":15},"loop":{"output":"","Time":12}},"quickjs-emscripten-cli":{"array":{"output":"5","Time":198},"loop":{"output":"52","Time":127}}}